<?xml version="1.0" encoding="utf-8"?>
<page color="#7EB14F" watermark="sprout_desat.png" bigbuttons="2">
  <title mode="straight" h="60">
    <heading textalign="center" translate="true" tnt-trx-ref-value="THESE CIRCLES DESCRIBE TWO TYPES OF PEOPLE" tnt-trx-translated="true">วงกลมสองวงนี้อธิบายถึงชีวิตสองแบบ</heading>
  </title>
  <button mode="big">
    <image align="center">SelfDirected.png</image>
    <buttontext translate="true" tnt-trx-ref-value="Self-Directed Person" tnt-trx-translated="true">ชีวิตตามใจตัวเอง</buttontext>
    <panel>
      <text size="80" textalign="center" w="265" translate="true" tnt-trx-ref-value="s - Self is in control and " tnt-trx-translated="true">s - ตนเองควบคุม </text>
      <text size="80" textalign="center" w="265" translate="true" tnt-trx-ref-value="✝ - Jesus has no influence in my life." tnt-trx-translated="true">✝ - พระเยซูไม่มีอิทธิพลในชีวิต</text>
      <text textalign="center" yoffset="20" w="265" h="82" translate="true" tnt-trx-ref-value="People like this have never received Jesus into their lives. They remain guilty and cut off from God by their sin." tnt-trx-translated="true">คนเหล่านี้ไม่เคยต้อนรับพระเยซูเข้ามาในชีวิต พวกเขายังคงมีความผิดและถูกตัดขาดจากพระเจ้าเพราะบาปของตน</text>
    </panel>
  </button>
  <button mode="big">
    <image align="center">ChristDirected.png</image>
    <buttontext translate="true" tnt-trx-ref-value="Christ-Directed Person" tnt-trx-translated="true">ชีวิตที่ให้พระเยซูครอบครอง</buttontext>
    <panel>
      <text size="80" textalign="center" w="265" translate="true" tnt-trx-ref-value="✝ - Jesus is in control and" tnt-trx-translated="true">✝ - พระเยซูเป็นผู้ควบคุมและ</text>
      <text size="80" textalign="center" w="265" translate="true" tnt-trx-ref-value="s - Self is following Jesus as Lord." tnt-trx-translated="true">s - ตนเองลงจากบัลลังก์และติดตามพระเยซูคริสต์ผู้ทรงเป็นพระเจ้า</text>
      <text textalign="center" yoffset="20" w="265" h="82" translate="true" tnt-trx-ref-value="People like this have received Jesus into their lives. They have been forgiven and experience God's love." tnt-trx-translated="true">บุคคลประเภทนี้ได้ต้อนรับพระเยซูคริสต์เข้ามาในชีวิต พวกเขาได้รับกับอภัยโทษบาปและมีประสบการณ์กับความรักของพระเจ้า</text>
    </panel>
  </button>
  <question mode="straight" modifier="normal" size="100" translate="true" tnt-trx-ref-value="Which circle best describes you?&#xD;&#xA;Which would you like to describe you?" tnt-trx-translated="true">วงกลมไหนเปรียบเสมือนชีวิตของท่านในขณะนี้?
ท่านอยากให้ชีวิตของท่านเป็นเหมือนวงกลมไหน?</question>
</page>