<?xml version="1.0" encoding="utf-8"?>
<page color="#7EB14F" watermark="sprout_desat.png" buttons="6">
  <title h="60">
    <heading x="10" w="285" size="94" translate="true" tnt-trx-ref-value="HOW TO GROW AS A FOLLOWER &#xD;&#xA;OF JESUS:" tnt-trx-translated="true">CÓMO CRECER COMO UN SEGUIDOR 
DE JESUS​​:</heading>
  </title>
  <button>
    <buttontext size="140" translate="true" tnt-trx-ref-value="G et to Know God" tnt-trx-translated="true">C onversa con Dios</buttontext>
    <panel>
      <text yoffset="6" size="90" translate="true" tnt-trx-ref-value="Get to know God by reading the Bible daily.   (2 Timothy 3:14-17)" tnt-trx-translated="true">Conversa con Dios en oración diariamente.   (2 Timoteo 3:14-17)</text>
      <text yoffset="12" size="90" translate="true" tnt-trx-ref-value="Begin with the gospel of John or Mark." tnt-trx-translated="true">Comienza con el evangelio de Juan o Marcos.</text>
    </panel>
  </button>
  <button>
    <buttontext size="140" translate="true" tnt-trx-ref-value="R espond" tnt-trx-translated="true">R ecurre</buttontext>
    <panel>
      <text yoffset="6" size="90" translate="true" tnt-trx-ref-value="Respond to God in prayer." tnt-trx-translated="true">Recurre a Dios en oración.</text>
      <text yoffset="4" size="90" textalign="right">(Phillipians 4:6)</text>
    </panel>
  </button>
  <button>
    <buttontext size="140" translate="true" tnt-trx-ref-value="O bey" tnt-trx-translated="true">I nsiste</buttontext>
    <panel>
      <text yoffset="6" size="90" translate="true" tnt-trx-ref-value="Obey God Moment by Moment." tnt-trx-translated="true">Insiste en confiar a Dios cada aspecto de tu vida.</text>
      <text yoffset="4" size="90" textalign="right">(Luke 6:46-49)</text>
    </panel>
  </button>
  <button>
    <buttontext size="140" translate="true" tnt-trx-ref-value="W alk" tnt-trx-translated="true">S e</buttontext>
    <panel>
      <text yoffset="6" size="90" translate="true" tnt-trx-ref-value="Walk in the Power of the Holy Spirit." tnt-trx-translated="true">Se lleno del Espíritu Santo. Permítele dirigir y fortalecer tu vida diariamente para testificar.</text>
      <text yoffset="4" size="90" textalign="right">(Ephesians 3:14-21, 5:18)</text>
    </panel>
  </button>
  <button>
    <buttontext size="140" translate="true" tnt-trx-ref-value="T ell Others" tnt-trx-translated="true">T estifica</buttontext>
    <panel>
      <text yoffset="6" size="90" translate="true" tnt-trx-ref-value="Tell others about Jesus through our life and words." tnt-trx-translated="true">Testifica a otros de Cristo verbalmente y con tu vida.</text>
      <text yoffset="4" size="90" textalign="right">( Matthew 28:18-20;
2 Corinthians 5:17-20;
Ephesians 4:1)</text>
    </panel>
  </button>
  <button>
    <buttontext size="140" translate="true" tnt-trx-ref-value="H ave Fellowship" tnt-trx-translated="true">O bedece</buttontext>
    <panel>
      <text yoffset="6" size="90" translate="true" tnt-trx-ref-value="Have fellowship with other Christians.&#xD;&#xA;(Hebrews 10:25; Acts 2:42-47)" tnt-trx-translated="true">Obedece a Dios momento a momento. (Juan 14:21)</text>
      <text yoffset="12" size="90" translate="true" tnt-trx-ref-value="Find a church where Jesus is worshipped and the Bible is taught." tnt-trx-translated="true">Busca una iglesia donde Cristo sea exaltado y la Biblia enseñada.</text>
    </panel>
  </button>
  <question translate="true" tnt-trx-ref-value="Want to Know More?" tnt-trx-translated="true">¿Quieres saber más?</question>
</page>