<?xml version="1.0" encoding="utf-8"?>

<page color="#007486" watermark="sprout_desat.png" buttons="5">
	
	<title>
        <heading x="20" w="275" translate="true">IF YOU ASKED JESUS INTO YOUR LIFE AS SAVIOUR AND LORD, MANY THINGS HAVE HAPPENED, INCLUDING:</heading>
    </title>
	
	<button>
		<buttontext size="90" translate="true">Jesus Has Come Into Your life</buttontext>
		<panel>
			<text size="90" translate="true">Jesus has come into your life by the Holy Spirit and he will never leave you.</text>
            <text size="90" textalign="right" translate="true">(Hebrews 13:5)</text>
		</panel>
	</button>
	
	<button>
		<buttontext size="90" translate="true">Your Sins Have Been Forgiven</buttontext>
		<panel>
			<text size="90" translate="true">All your sins have been forgiven.</text>
            <text size="90" textalign="right" translate="true">(Colossians 1:13-14)</text>
		</panel>
	</button>
	
	<button>
		<buttontext size="90" translate="true">You Are Now a Child of God</buttontext>
		<panel>
			<text size="90" translate="true">You have become a child of God. He is your heavenly father.</text>
            <text size="90" textalign="right" translate="true">(Galatians 3:26)</text>
		</panel>
	</button>
	
	<button>
		<buttontext size="90" translate="true">You Have Been Empowered</buttontext>
		<panel>
			<text size="90" translate="true">God has given you new power to live a transformed life.</text>
            <text size="90" textalign="right" translate="true">(2 Corinthians 5:17; Ephesians 3:14-21)</text>
		</panel>
	</button>
	
	<button>
		<buttontext size="90" translate="true">You Are Now Friends with God</buttontext>
		<panel>
			<text size="90" translate="true">You have started a friendship with God that will last forever.</text>
            <text size="90" textalign="right" translate="true">(John 17:3)</text>
		</panel>
	</button>
	
	<question translate="true">But how do we know this
actually happened?</question>
	
</page>